tests/__init__.py
tests/test_wikiwhopickle.py
tests/test_wikiwhowrapper.py
wikiwho_wrapper/__init__.py
wikiwho_wrapper/api.py
wikiwho_wrapper/pickle_api.py
wikiwho_wrapper/views.py
wikiwho_wrapper/wikiwho.py
wikiwho_wrapper-1.6.4.dist-info/LICENSE
wikiwho_wrapper-1.6.4.dist-info/METADATA
wikiwho_wrapper-1.6.4.dist-info/WHEEL
wikiwho_wrapper-1.6.4.dist-info/top_level.txt
wikiwho_wrapper-1.6.4.dist-info/RECORD
