Metadata-Version: 2.1
Name: wikiwho-wrapper
Version: 1.6.4
Summary: A light/simple Python wrapper for the WikiWho API
Home-page: https://github.com/gesiscss/wikiwho_wrapper
Author: 
Author-email: wikiwho@gesis.org
License: UNKNOWN
Keywords: wikipedia wikiwho revisions content authorship
Platform: UNKNOWN
Classifier: Programming Language :: Python :: 3
Classifier: License :: OSI Approved :: MIT License
Classifier: Operating System :: OS Independent
Requires-Dist: requests
Requires-Dist: pandas
Requires-Dist: deprecation
Requires-Dist: wikiwho-pickle
